milvus_storage/__init__.py
milvus_storage/_ffi.py
milvus_storage/exceptions.py
milvus_storage/properties.py
milvus_storage/reader.py
milvus_storage/writer.py
milvus_storage/lib/libmilvus-storage.so
milvus_storage-0.1.0.dev1.dist-info/METADATA
milvus_storage-0.1.0.dev1.dist-info/WHEEL
milvus_storage-0.1.0.dev1.dist-info/top_level.txt
milvus_storage-0.1.0.dev1.dist-info/RECORD
