Metadata-Version: 2.4
Name: milvus-storage
Version: 0.1.0.dev1
Summary: Python bindings for milvus-storage - a high-performance storage engine using Apache Arrow Parquet
Author-email: Zilliz <dev@zilliz.com>
Maintainer-email: Zilliz <dev@zilliz.com>
License: Apache-2.0
Project-URL: Homepage, https://github.com/milvus-io/milvus-storage
Project-URL: Documentation, https://github.com/milvus-io/milvus-storage
Project-URL: Repository, https://github.com/milvus-io/milvus-storage
Project-URL: Bug Tracker, https://github.com/milvus-io/milvus-storage/issues
Keywords: milvus,storage,arrow,parquet,vector-database
Classifier: Development Status :: 3 - Alpha
Classifier: Intended Audience :: Developers
Classifier: Topic :: Database
Classifier: Topic :: Scientific/Engineering
Classifier: License :: OSI Approved :: Apache Software License
Classifier: Programming Language :: Python :: 3
Classifier: Programming Language :: Python :: 3.9
Classifier: Programming Language :: Python :: 3.10
Classifier: Programming Language :: Python :: 3.11
Classifier: Programming Language :: Python :: 3.12
Classifier: Operating System :: POSIX :: Linux
Classifier: Operating System :: MacOS
Requires-Python: >=3.9
Requires-Dist: pyarrow>=21.0.0
Requires-Dist: numpy>=1.20.0
Requires-Dist: cffi>=1.17.1
Requires-Dist: pandas>=2.3.3
Provides-Extra: dev
Requires-Dist: pytest>=7.0.0; extra == "dev"
Requires-Dist: pytest-cov>=4.0.0; extra == "dev"
Requires-Dist: black>=22.0.0; extra == "dev"
Requires-Dist: flake8>=5.0.0; extra == "dev"
Requires-Dist: mypy>=0.990; extra == "dev"
Provides-Extra: test
Requires-Dist: pytest>=7.0.0; extra == "test"
Requires-Dist: pytest-cov>=4.0.0; extra == "test"
